go_api/__init__.py
go_api/utils.py
go_api/collections/__init__.py
go_api/collections/errors.py
go_api/collections/inmemory.py
go_api/collections/interfaces.py
go_api/collections/tests/__init__.py
go_api/collections/tests/test_errors.py
go_api/collections/tests/test_inmemory.py
go_api/cyclone/__init__.py
go_api/cyclone/handlers.py
go_api/cyclone/helpers.py
go_api/cyclone/tests/__init__.py
go_api/cyclone/tests/test_handlers.py
go_api/queue/__init__.py
go_api/queue/pausingdeferredqueue.py
go_api/queue/tests/__init__.py
go_api/queue/tests/test_pausing_deferred_queue.py
go_api/tests/__init__.py
go_api/tests/test_utils.py
go_api-0.3.1.dist-info/DESCRIPTION.rst
go_api-0.3.1.dist-info/METADATA
go_api-0.3.1.dist-info/RECORD
go_api-0.3.1.dist-info/WHEEL
go_api-0.3.1.dist-info/metadata.json
go_api-0.3.1.dist-info/top_level.txt
