Metadata-Version: 2.0
Name: go-api
Version: 0.3.1
Summary: A toolkit for building Vumi Go APIs
Home-page: http://github.com/praekelt/go-api-toolkit
Author: Praekelt Foundation
Author-email: dev@praekeltfoundation.org
License: BSD
Platform: UNKNOWN
Classifier: Development Status :: 4 - Beta
Classifier: Intended Audience :: Developers
Classifier: License :: OSI Approved :: BSD License
Classifier: Operating System :: POSIX
Classifier: Programming Language :: Python
Classifier: Topic :: Software Development :: Libraries :: Python Modules
Classifier: Topic :: Internet :: WWW/HTTP
Requires-Dist: PyYAML
Requires-Dist: cyclone
Requires-Dist: treq
Requires-Dist: zope.interface
